setup.cfg
setup.py
actontext/__init__.py
actontext/commandor.py
actontext.egg-info/PKG-INFO
actontext.egg-info/SOURCES.txt
actontext.egg-info/dependency_links.txt
actontext.egg-info/requires.txt
actontext.egg-info/top_level.txt
native/actonext.cpp