Metadata-Version: 2.1
Name: actontext
Version: 0.2.2
Summary: This module provides functions to load COM DLL on Windows machine, to avoid registering it in Windows registry.
Home-page: https://github.com/mettizik/pyactontext
Author: Mokych Andrey
Author-email: mokych.apriorit@gmail.com
License: MIT
Download-URL: https://github.com/mettizik/pyactontext/archive/v0.2.2.tar.gz
Keywords: COM,ATL,side-by-side,activation context
Platform: UNKNOWN
Classifier: Development Status :: 3 - Alpha
Classifier: Intended Audience :: Developers
Classifier: Topic :: Software Development :: Build Tools
Classifier: License :: OSI Approved :: MIT License
Classifier: Programming Language :: Python :: 3
Classifier: Programming Language :: Python :: 3.4
Classifier: Programming Language :: Python :: 3.5
Classifier: Programming Language :: Python :: 3.6
Classifier: Programming Language :: Python :: 3.7
Classifier: Operating System :: Microsoft :: Windows
